README.md
setup.py
rumax/__init__.py
rumax/client.py
rumax/exceptions.py
rumax/filters.py
rumax/handlers.py
rumax/network.py
rumax/sync.py
rumax/utils.py
rumax.egg-info/PKG-INFO
rumax.egg-info/SOURCES.txt
rumax.egg-info/dependency_links.txt
rumax.egg-info/requires.txt
rumax.egg-info/top_level.txt
rumax/bots/__init__.py
rumax/bots/client.py
rumax/bots/types/__init__.py
rumax/bots/types/aux_data.py
rumax/bots/types/bot.py
rumax/bots/types/bot_command.py
rumax/bots/types/button.py
rumax/bots/types/button_calendar.py
rumax/bots/types/button_location.py
rumax/bots/types/button_number_picker.py
rumax/bots/types/button_selection.py
rumax/bots/types/button_selection_item.py
rumax/bots/types/button_string_picker.py
rumax/bots/types/button_textbox.py
rumax/bots/types/chat.py
rumax/bots/types/contact_message.py
rumax/bots/types/file.py
rumax/bots/types/forwarded_from.py
rumax/bots/types/inline_message.py
rumax/bots/types/keypad.py
rumax/bots/types/keypad_row.py
rumax/bots/types/live_location.py
rumax/bots/types/location.py
rumax/bots/types/messaage_text_update.py
rumax/bots/types/message.py
rumax/bots/types/message_keypad_update.py
rumax/bots/types/payment_status.py
rumax/bots/types/poll.py
rumax/bots/types/poll_status.py
rumax/bots/types/sticker.py
rumax/bots/types/update.py
rumax/crypto/__init__.py
rumax/crypto/crypto.py
rumax/enums/__init__.py
rumax/enums/chat_access_type.py
rumax/enums/chat_action.py
rumax/enums/chat_type.py
rumax/enums/message_media_type.py
rumax/enums/parse_mode.py
rumax/enums/poll_type.py
rumax/enums/reaction_type.py
rumax/enums/report_type.py
rumax/methods/__init__.py
rumax/methods/advanced/__init__.py
rumax/methods/advanced/build.py
rumax/methods/advanced/voice_chat_player.py
rumax/methods/auth/__init__.py
rumax/methods/auth/register_device.py
rumax/methods/auth/send_code.py
rumax/methods/auth/sign_in.py
rumax/methods/channels/__init__.py
rumax/methods/channels/add_channel.py
rumax/methods/channels/add_channel_members.py
rumax/methods/channels/ban_channel_member.py
rumax/methods/channels/channel_preview_by_join_link.py
rumax/methods/channels/check_channel_username.py
