Metadata-Version: 2.1
Name: rumax
Version: 0.1
Summary: A powerful, fast and optimal library for making robots in Rubika with sync and async support.
Home-page: https://github.com/rumaxproject/rumax
Author: Shayan Heidari
Author-email: contact@shayanheidari.info
Keywords: rubika,rubpy,chat,bot,robot,asyncio
Classifier: Programming Language :: Python :: 3.7
Classifier: Programming Language :: Python :: 3.8
Classifier: Programming Language :: Python :: 3.9
Classifier: Programming Language :: Python :: 3.10
Classifier: Programming Language :: Python :: 3.11
Classifier: Programming Language :: Python :: 3.12
Classifier: Programming Language :: Python :: 3.13
Classifier: License :: OSI Approved :: GNU Lesser General Public License v3 (LGPLv3)
Classifier: Topic :: Internet
Classifier: Topic :: Communications
Classifier: Topic :: Communications :: Chat
Classifier: Topic :: Software Development :: Libraries
Classifier: Topic :: Software Development :: Libraries :: Python Modules
Classifier: Topic :: Software Development :: Libraries :: Application Frameworks
Requires-Python: ~=3.7
Provides-Extra: cv
Provides-Extra: movie
Provides-Extra: pil
Provides-Extra: rtc
